README.md
setup.py
dingding_sdk.egg-info/PKG-INFO
dingding_sdk.egg-info/SOURCES.txt
dingding_sdk.egg-info/dependency_links.txt
dingding_sdk.egg-info/requires.txt
dingding_sdk.egg-info/top_level.txt
dingding_sdk.egg-info/zip-safe
dingtalk/__init__.py
dingtalk/contact.py
dingtalk/core.py
dingtalk/dingtalk.py
dingtalk/document.py
dingtalk/exceptions.py
dingtalk/hr.py
dingtalk/message.py
dingtalk/oauth.py
dingtalk/robot.py
dingtalk/session.py
dingtalk/space.py
dingtalk/workflow.py
tests/__init__.py
tests/test_contact.py
tests/test_core.py
tests/test_document.py
tests/test_hr.py
tests/test_message.py
tests/test_robot.py
tests/test_session.py
tests/test_space.py
tests/test_workflow.py