Metadata-Version: 2.1
Name: dingding-sdk
Version: 0.0.7
Summary: DingTalk Python SDK
Home-page: https://github.com/jellyhappy/dingding-sdk
Author: blackcat
Author-email: kfx2007@163.com
License: GNU
Keywords: dingding sdk
Platform: UNKNOWN
Classifier: License :: OSI Approved :: GNU Affero General Public License v3
Classifier: Programming Language :: Python
Classifier: Operating System :: OS Independent
Classifier: Topic :: Scientific/Engineering :: Astronomy
Classifier: Topic :: Scientific/Engineering :: GIS
Classifier: Topic :: Scientific/Engineering :: Mathematics
Classifier: Intended Audience :: Science/Research
Classifier: Intended Audience :: Developers
Classifier: Intended Audience :: Information Technology
